aios3/__about__.py
aios3/__init__.py
aios3/file.py
aios3/stream_iter.py
aios3-1.0.4.dist-info/METADATA
aios3-1.0.4.dist-info/WHEEL
aios3-1.0.4.dist-info/licenses/LICENSE.txt
aios3-1.0.4.dist-info/RECORD
