Metadata-Version: 2.4
Name: aios3
Version: 1.0.4
Summary: Wrapper for aiobotocore to simplify reading of large files
Project-URL: Homepage, https://andgineer.github.io/aios3/
Project-URL: documentation, https://andgineer.github.io/aios3/
Author-email: Andrey Sorokin <andrey@sorokin.engineer>
License: Copyright (c) 2021 Andrey Sorokin <andrey@sorokin.engineer>
License-File: LICENSE.txt
Keywords: asyncio,aws,boto3,botocore,s3
Classifier: License :: OSI Approved :: MIT License
Classifier: Operating System :: OS Independent
Classifier: Programming Language :: Python :: 3
Requires-Python: >=3.10
Requires-Dist: aiobotocore
Requires-Dist: multidict>=6.0.5
